table_recipe.py
parser_table_salamandra1997-0.0.1.dist-info/licenses/LICENSE.txt
parser_table_salamandra1997-0.0.1.dist-info/METADATA
parser_table_salamandra1997-0.0.1.dist-info/WHEEL
parser_table_salamandra1997-0.0.1.dist-info/top_level.txt
parser_table_salamandra1997-0.0.1.dist-info/RECORD
